setup.py
GiHa_Docs.egg-info/PKG-INFO
GiHa_Docs.egg-info/SOURCES.txt
GiHa_Docs.egg-info/dependency_links.txt
GiHa_Docs.egg-info/entry_points.txt
GiHa_Docs.egg-info/not-zip-safe
GiHa_Docs.egg-info/requires.txt
GiHa_Docs.egg-info/top_level.txt
gihadocs/__init__.py
gihadocs/__main__.py
gihadocs/exceptions.py
gihadocs/plugins.py
gihadocs/theme.py
gihadocs/commands/__init__.py
gihadocs/commands/build.py
gihadocs/commands/gh_deploy.py
gihadocs/commands/new.py
gihadocs/commands/serve.py
gihadocs/config/__init__.py
gihadocs/config/base.py
gihadocs/config/config_options.py
gihadocs/config/defaults.py
gihadocs/contrib/__init__.py
gihadocs/contrib/search/__init__.py
gihadocs/contrib/search/search_index.py
gihadocs/structure/__init__.py
gihadocs/structure/files.py
gihadocs/structure/nav.py
gihadocs/structure/pages.py
gihadocs/structure/toc.py
gihadocs/tests/__init__.py
gihadocs/tests/base.py
gihadocs/tests/build_tests.py
gihadocs/tests/cli_tests.py
gihadocs/tests/gh_deploy_tests.py
gihadocs/tests/integration.py
gihadocs/tests/new_tests.py
gihadocs/tests/plugin_tests.py
gihadocs/tests/search_tests.py
gihadocs/tests/theme_tests.py
gihadocs/tests/config/__init__.py
gihadocs/tests/config/base_tests.py
gihadocs/tests/config/config_options_tests.py
gihadocs/tests/config/config_tests.py
gihadocs/tests/structure/__init__.py
gihadocs/tests/structure/file_tests.py
gihadocs/tests/structure/nav_tests.py
gihadocs/tests/structure/page_tests.py
gihadocs/tests/structure/toc_tests.py
gihadocs/tests/utils/__init__.py
gihadocs/tests/utils/ghp_import_tests.py
gihadocs/tests/utils/utils_tests.py
gihadocs/themes/__init__.py
gihadocs/themes/gihadocs/__init__.py
gihadocs/themes/readthedocs/__init__.py
gihadocs/utils/__init__.py
gihadocs/utils/filters.py
gihadocs/utils/ghp_import.py
gihadocs/utils/meta.py